fastapi_intelligent_cache/__init__.py
fastapi_intelligent_cache/admin/__init__.py
fastapi_intelligent_cache/admin/routes.py
fastapi_intelligent_cache/backends/__init__.py
fastapi_intelligent_cache/backends/base.py
fastapi_intelligent_cache/backends/memory.py
fastapi_intelligent_cache/backends/redis.py
fastapi_intelligent_cache/decorator.py
fastapi_intelligent_cache/dependencies.py
fastapi_intelligent_cache/invalidation.py
fastapi_intelligent_cache/key_generator.py
fastapi_intelligent_cache/manager.py
fastapi_intelligent_cache/middleware.py
fastapi_intelligent_cache/service.py
fastapi_intelligent_cache-0.1.4.dist-info/METADATA
fastapi_intelligent_cache-0.1.4.dist-info/WHEEL
fastapi_intelligent_cache-0.1.4.dist-info/licenses/LICENSE
fastapi_intelligent_cache-0.1.4.dist-info/RECORD
