Metadata-Version: 2.4
Name: fastapi-intelligent-cache
Version: 0.1.4
Summary: Intelligent caching library for FastAPI with automatic invalidation
License-File: LICENSE
Author: Cloud11 Team
Requires-Python: >=3.8,<4.0
Classifier: Programming Language :: Python :: 3
Classifier: Programming Language :: Python :: 3.8
Classifier: Programming Language :: Python :: 3.9
Classifier: Programming Language :: Python :: 3.10
Classifier: Programming Language :: Python :: 3.11
Classifier: Programming Language :: Python :: 3.12
Classifier: Programming Language :: Python :: 3.13
Classifier: Programming Language :: Python :: 3.14
Provides-Extra: redis
Requires-Dist: fastapi (>=0.109.0)
Requires-Dist: pydantic (>=2.5.0,<3.0.0)
Requires-Dist: pydantic-settings (>=2.1.0,<3.0.0)
Requires-Dist: redis (>=5.0.0,<6.0.0) ; extra == "redis"
